src/.gitkeep
src/__init__.py
src/anonymisation/.gitkeep
src/anonymisation/__init__.py
src/anonymisation/synthesis.py
src/anonymizer.py
src/evaluations/.gitkeep
src/evaluations/__init__.py
src/evaluations/anonymity_evaluation/__init__.py
src/evaluations/anonymity_evaluation/anonymity_evaluator.py
src/evaluations/quality_evaluation/__init__.py
src/evaluations/quality_evaluation/quality_evaluator.py
src/preprocessing/.gitkeep
src/preprocessing/__init__.py
src/preprocessing/data_processor.py
src/preprocessing/get_metadata.py
anonymizerada-0.1.0.dist-info/LICENSE
anonymizerada-0.1.0.dist-info/METADATA
anonymizerada-0.1.0.dist-info/WHEEL
anonymizerada-0.1.0.dist-info/RECORD
